phased_array/__init__.py
phased_array/_version.py
phased_array/phased_array.py
phased_array-0.0.0.dist-info/METADATA
phased_array-0.0.0.dist-info/WHEEL
phased_array-0.0.0.dist-info/top_level.txt
phased_array-0.0.0.dist-info/RECORD
