Metadata-Version: 2.4
Name: phased_array
Version: 0.0.0
Summary: Tools for dealing with phased arrays
Author-email: Cody Piersall <cody.piersall@gmail.com>
Keywords: radar,antenna,phased array
Requires-Python: >=3.8
Requires-Dist: numpy
